bsmschema/__init__.py
bsmschema/__main__.py
bsmschema/models.py
bsmschema/py.typed
bsmschema-0.1.1.dist-info/METADATA
bsmschema-0.1.1.dist-info/WHEEL
bsmschema-0.1.1.dist-info/licenses/LICENSE
bsmschema-0.1.1.dist-info/RECORD
