Metadata-Version: 2.4
Name: bsmschema
Version: 0.1.1
Summary: A Pydantic schema for BIDS Stats Models
Project-URL: Homepage, https://bids-standard.github.io/stats-models/
Project-URL: Source code, https://github.com/bids-standard/stats-models
Author-email: BIDS Contributors <bids.maintenance@gmail.com>
License:                                  Apache License
License-File: LICENSE
Classifier: Development Status :: 4 - Beta
Classifier: License :: OSI Approved :: Apache Software License
Classifier: Programming Language :: Python :: 3
Classifier: Programming Language :: Python :: 3.9
Classifier: Programming Language :: Python :: 3.10
Classifier: Programming Language :: Python :: 3.11
Classifier: Programming Language :: Python :: 3.12
Classifier: Programming Language :: Python :: 3.13
Requires-Python: >=3.9
Requires-Dist: pydantic>=2
